{"../public/img/sentinel/sentinel_0.jpg": {"correct_code": "P35", "coordinate": [586, 402], "correct_codes": ["S16", "T83", "N36", "P35", "J65", "F26", "A86", "C19", "L93", "P26"]}, "../public/img/sentinel/sentinel_1.jpg": {"correct_code": "W25", "coordinate": [619, 545], "correct_codes": ["A65", "B51", "F95", "K47", "M74", "T96", "C48", "W25", "J75", "F62"]}, "../public/img/sentinel/sentinel_2.jpg": {"correct_code": "H89", "coordinate": [599, 536], "correct_codes": ["W76", "Z59", "H89", "N98", "Q53", "V19", "C47", "R25", "D13", "T98"]}, "../public/img/sentinel/sentinel_3.jpg": {"correct_code": "T24", "coordinate": [383, 505], "correct_codes": ["T24", "V14", "J93", "E89", "B92", "N43", "F93", "M76", "H29", "G62"]}, "../public/img/sentinel/sentinel_4.jpg": {"correct_code": "L78", "coordinate": [832, 279], "correct_codes": ["X87", "L78", "J79", "E19", "L47", "U28", "M47"]}, "../public/img/sentinel/sentinel_5.jpg": {"correct_code": "Q31", "coordinate": [746, 383], "correct_codes": ["A69", "J21", "L38", "N98", "D79", "A18", "Q64", "Y48", "D62", "Q31"]}, "../public/img/sentinel/sentinel_6.jpg": {"correct_code": "D72", "coordinate": [606, 225], "correct_codes": ["V28", "C98", "C45", "D72", "Y92", "J96", "T78", "N78", "T58", "D58", "G79"]}, "../public/img/sentinel/sentinel_7.jpg": {"correct_code": "Y82", "coordinate": [926, 127], "correct_codes": ["Y82", "Y92", "J48", "Y79", "D15", "H47", "X57", "R96", "E54", "W84"]}, "../public/img/sentinel/sentinel_8.jpg": {"correct_code": "V93", "coordinate": [434, 512], "correct_codes": ["V93", "S94", "D61", "P14", "E12", "W73", "V91", "E95", "Y21"]}, "../public/img/sentinel/sentinel_9.jpg": {"correct_code": "Y32", "coordinate": [187, 395], "correct_codes": ["X58", "Y32", "D25", "L53", "W89", "E64", "R19", "J43", "N92", "L61"]}, "../public/img/sentinel/sentinel_10.jpg": {"correct_code": "T29", "coordinate": [1001, 265], "correct_codes": ["V79", "U59", "B29", "S94", "D92", "X97", "K15", "T29", "T62"]}, "../public/img/sentinel/sentinel_11.jpg": {"correct_code": "R47", "coordinate": [1073, 506], "correct_codes": ["Y56", "B63", "X42", "A31", "L69", "B12", "S69", "S52", "Y48", "R47"]}, "../public/img/sentinel/sentinel_12.jpg": {"correct_code": "Q54", "coordinate": [440, 600], "correct_codes": ["Y25", "R72", "Q16", "P35", "Q54", "P36", "Y67", "V89"]}, "../public/img/sentinel/sentinel_13.jpg": {"correct_code": "B35", "coordinate": [1098, 482], "correct_codes": ["E67", "U86", "Z87", "B35", "G86", "Q67", "A96", "L84", "Y67"]}, "../public/img/sentinel/sentinel_14.jpg": {"correct_code": "W17", "coordinate": [1073, 600], "correct_codes": ["W68", "P42", "N68", "L79", "D95", "W17", "F87", "Q82", "P26"]}, "../public/img/sentinel/sentinel_15.jpg": {"correct_code": "W97", "coordinate": [508, 436], "correct_codes": ["S16", "A47", "D24", "U53", "S49", "W97", "Q76", "L29"]}, "../public/img/sentinel/sentinel_16.jpg": {"correct_code": "L61", "coordinate": [274, 598], "correct_codes": ["P46", "W56", "Y12", "W83", "N36", "K61", "L61", "N87", "Y83", "Y16"]}, "../public/img/sentinel/sentinel_17.jpg": {"correct_code": "T79", "coordinate": [1032, 582], "correct_codes": ["W35", "E52", "Y92", "E71", "M91", "V98", "H16", "U89", "T79", "D38", "Q62"]}, "../public/img/sentinel/sentinel_18.jpg": {"correct_code": "H57", "coordinate": [1089, 272], "correct_codes": ["T52", "L42", "L12", "N36", "J72", "V85", "C47", "Q12", "D46", "H57", "C65"]}, "../public/img/sentinel/sentinel_19.jpg": {"correct_code": "K53", "coordinate": [653, 540], "correct_codes": ["D54", "Z85", "B52", "Z89", "K53", "E62", "D68", "G83", "R13"]}, "../public/img/sentinel/sentinel_20.jpg": {"correct_code": "P83", "coordinate": [869, 493], "correct_codes": ["T52", "E98", "P83", "N34", "N86", "L73", "M94", "E28"]}, "../public/img/sentinel/sentinel_21.jpg": {"correct_code": "K29", "coordinate": [119, 342], "correct_codes": ["K29", "T78", "E46", "Z91", "C14", "E58", "L65", "P93", "S84", "E94"]}, "../public/img/sentinel/sentinel_22.jpg": {"correct_code": "Q78", "coordinate": [860, 333], "correct_codes": ["K73", "N63", "N71", "Q78", "U96", "H68", "B12", "L84", "X15"]}, "../public/img/sentinel/sentinel_23.jpg": {"correct_code": "R56", "coordinate": [834, 285], "correct_codes": ["Z45", "G26", "Z98", "S29", "F29", "J78", "R56", "L37", "Z36", "E37"]}, "../public/img/sentinel/sentinel_24.jpg": {"correct_code": "E89", "coordinate": [1109, 607], "correct_codes": ["Q87", "L68", "E89", "G86", "H53", "D71", "F93", "Y67"]}, "../public/img/sentinel/sentinel_25.jpg": {"correct_code": "C84", "coordinate": [841, 432], "correct_codes": ["C37", "L74", "U38", "C84", "D27", "C79", "K49", "E35", "R79", "F98"]}, "../public/img/sentinel/sentinel_26.jpg": {"correct_code": "H32", "coordinate": [1169, 540], "correct_codes": ["T92", "Z64", "H32", "M91", "A75", "U79", "X43"]}, "../public/img/sentinel/sentinel_27.jpg": {"correct_code": "V14", "coordinate": [522, 288], "correct_codes": ["W56", "H14", "Z14", "R26", "V14", "Z43", "F91", "M79", "S98", "K28", "K81"]}, "../public/img/sentinel/sentinel_28.jpg": {"correct_code": "L41", "coordinate": [1006, 348], "correct_codes": ["G57", "E72", "B95", "V57", "L41", "P24", "K37", "W36", "R95", "Q17"]}, "../public/img/sentinel/sentinel_29.jpg": {"correct_code": "V17", "coordinate": [337, 392], "correct_codes": ["S28", "K17", "B32", "C75", "X74", "Y35", "N53", "R49", "L59", "V17"]}, "../public/img/sentinel/sentinel_30.jpg": {"correct_code": "X29", "coordinate": [1106, 108], "correct_codes": ["X29", "J79", "A85", "Z34", "A36", "D83", "Q79", "T65", "X45", "P71"]}, "../public/img/sentinel/sentinel_31.jpg": {"correct_code": "N87", "coordinate": [539, 181], "correct_codes": ["F56", "E97", "G13", "E45", "J92", "P14", "L18", "N87", "V76"]}, "../public/img/sentinel/sentinel_32.jpg": {"correct_code": "A29", "coordinate": [747, 338], "correct_codes": ["Q75", "X73", "U39", "M38", "W49", "C23", "A29", "K14", "P84", "Z31"]}, "../public/img/sentinel/sentinel_33.jpg": {"correct_code": "V63", "coordinate": [1092, 617], "correct_codes": ["V63", "W81", "S82", "V65", "Q36", "N94", "W51", "A59", "R42"]}, "../public/img/sentinel/sentinel_34.jpg": {"correct_code": "M68", "coordinate": [682, 346], "correct_codes": ["Q75", "U94", "M73", "M68", "T72", "K85", "M51", "X14", "J54"]}, "../public/img/sentinel/sentinel_35.jpg": {"correct_code": "Y75", "coordinate": [1072, 166], "correct_codes": ["G34", "N75", "P57", "Y75", "H76", "V64", "W45", "P94", "B17", "W98"]}, "../public/img/sentinel/sentinel_36.jpg": {"correct_code": "S87", "coordinate": [1097, 429], "correct_codes": ["F41", "S96", "N42", "N51", "C84", "S87", "M12", "W53", "A61", "T35", "S65"]}, "../public/img/sentinel/sentinel_37.jpg": {"correct_code": "G53", "coordinate": [627, 397], "correct_codes": ["C37", "Z15", "W32", "Q19", "K65", "K29", "E84", "C64", "W36", "G53"]}, "../public/img/sentinel/sentinel_38.jpg": {"correct_code": "T26", "coordinate": [764, 393], "correct_codes": ["N18", "V24", "V93", "X35", "X48", "S97", "E63", "T26", "Y51"]}, "../public/img/sentinel/sentinel_39.jpg": {"correct_code": "W45", "coordinate": [267, 330], "correct_codes": ["P95", "V69", "T19", "J98", "K32", "W45", "A59", "H15", "S21"]}, "../public/img/sentinel/sentinel_40.jpg": {"correct_code": "H35", "coordinate": [701, 477], "correct_codes": ["U49", "V13", "U41", "H35", "M47", "K35", "M51", "D76", "B74", "Y42"]}, "../public/img/sentinel/sentinel_41.jpg": {"correct_code": "M97", "coordinate": [996, 445], "correct_codes": ["Z26", "N49", "J68", "M97", "F76", "U89", "D62", "F83", "L85", "X62"]}, "../public/img/sentinel/sentinel_42.jpg": {"correct_code": "C45", "coordinate": [994, 443], "correct_codes": ["F46", "Y93", "A93", "C45", "N63", "M83", "M34", "M57", "X51", "W17", "J18"]}, "../public/img/sentinel/sentinel_43.jpg": {"correct_code": "L94", "coordinate": [324, 172], "correct_codes": ["B51", "Y86", "H81", "C34", "L68", "E19", "A29", "Y14", "L94", "S34"]}, "../public/img/sentinel/sentinel_44.jpg": {"correct_code": "Q85", "coordinate": [353, 103], "correct_codes": ["Q85", "K91", "J46", "B38", "E46", "H28", "P81", "T25", "U61", "Y37"]}, "../public/img/sentinel/sentinel_45.jpg": {"correct_code": "B15", "coordinate": [686, 332], "correct_codes": ["P63", "P75", "J26", "C59", "L74", "Y45", "B15", "U28", "H34", "H86", "G59"]}, "../public/img/sentinel/sentinel_46.jpg": {"correct_code": "N17", "coordinate": [165, 120], "correct_codes": ["D64", "Y19", "Y41", "M74", "M57", "R93", "Q67", "X31", "N17", "F16", "Q95"]}, "../public/img/sentinel/sentinel_47.jpg": {"correct_code": "W13", "coordinate": [361, 613], "correct_codes": ["Q14", "W49", "N68", "W13", "H87", "R64", "X14", "J53", "W96"]}, "../public/img/sentinel/sentinel_48.jpg": {"correct_code": "T84", "coordinate": [941, 501], "correct_codes": ["N65", "T84", "R18", "H61", "A23", "D76", "G39", "Q93", "P26"]}, "../public/img/sentinel/sentinel_49.jpg": {"correct_code": "U26", "coordinate": [197, 178], "correct_codes": ["N48", "P75", "V28", "M25", "A38", "R91", "R43", "J87", "U26", "Y42"]}, "../public/img/sentinel/sentinel_50.jpg": {"correct_code": "V36", "coordinate": [587, 185], "correct_codes": ["N48", "D29", "V36", "Y17", "K29", "D17", "X63", "M47", "Q38", "R63"]}, "../public/img/sentinel/sentinel_51.jpg": {"correct_code": "G76", "coordinate": [1079, 503], "correct_codes": ["S83", "N85", "C21", "K82", "G76", "E83", "B43", "Y96"]}, "../public/img/sentinel/sentinel_52.jpg": {"correct_code": "U26", "coordinate": [1112, 582], "correct_codes": ["T97", "J21", "F61", "S82", "S13", "Y46", "R64", "R25", "U26", "L65", "G53"]}, "../public/img/sentinel/sentinel_53.jpg": {"correct_code": "U72", "coordinate": [1108, 293], "correct_codes": ["C94", "J38", "F51", "C72", "Q52", "K36", "S53", "R15", "U72", "P85"]}, "../public/img/sentinel/sentinel_54.jpg": {"correct_code": "E98", "coordinate": [1036, 249], "correct_codes": ["E98", "P96", "V54", "G64", "H18", "G37", "Z58"]}, "../public/img/sentinel/sentinel_55.jpg": {"correct_code": "A76", "coordinate": [358, 292], "correct_codes": ["Y47", "X94", "G27", "A76", "Q19", "X63", "L45", "B81", "S26", "Y84"]}, "../public/img/sentinel/sentinel_56.jpg": {"correct_code": "D17", "coordinate": [103, 538], "correct_codes": ["G94", "J51", "H71", "J52", "D17", "Q79", "P68", "F23", "N72"]}, "../public/img/sentinel/sentinel_57.jpg": {"correct_code": "W76", "coordinate": [844, 230], "correct_codes": ["W76", "Y36", "L25", "X75", "B95", "A84", "K71", "S39", "L61"]}, "../public/img/sentinel/sentinel_58.jpg": {"correct_code": "Q75", "coordinate": [694, 504], "correct_codes": ["Q75", "T89", "N63", "L31", "V75", "V94", "M81", "M34", "R23", "D93"]}, "../public/img/sentinel/sentinel_59.jpg": {"correct_code": "J53", "coordinate": [436, 384], "correct_codes": ["V27", "X42", "P18", "R32", "X89", "X56", "Z24", "J53", "Z75", "S34"]}, "../public/img/sentinel/sentinel_60.jpg": {"correct_code": "F21", "coordinate": [1023, 489], "correct_codes": ["F25", "M72", "E67", "F79", "C17", "F21", "A86", "C69", "B89", "K54", "B24"]}, "../public/img/sentinel/sentinel_61.jpg": {"correct_code": "P54", "coordinate": [1084, 340], "correct_codes": ["S71", "W69", "D49", "F31", "K61", "R51", "C61", "M17", "K58", "P54"]}, "../public/img/sentinel/sentinel_62.jpg": {"correct_code": "W46", "coordinate": [253, 542], "correct_codes": ["W39", "E36", "J81", "D59", "J79", "J38", "H68", "U73", "W46", "P78"]}, "../public/img/sentinel/sentinel_63.jpg": {"correct_code": "R82", "coordinate": [595, 285], "correct_codes": ["V36", "N58", "R38", "Q73", "D51", "K29", "R82", "T81", "K97"]}, "../public/img/sentinel/sentinel_64.jpg": {"correct_code": "K53", "coordinate": [902, 480], "correct_codes": ["B26", "E31", "Y92", "F75", "U96", "H83", "K53", "H34", "N17", "Q59"]}, "../public/img/sentinel/sentinel_65.jpg": {"correct_code": "M64", "coordinate": [784, 388], "correct_codes": ["S25", "P18", "S31", "Z62", "T39", "Y39", "T65", "M64", "W54", "B17"]}, "../public/img/sentinel/sentinel_66.jpg": {"correct_code": "S79", "coordinate": [592, 169], "correct_codes": ["P97", "S76", "Z83", "D36", "Y59", "W29", "Z16", "R92", "M37", "S79"]}, "../public/img/sentinel/sentinel_67.jpg": {"correct_code": "R76", "coordinate": [850, 323], "correct_codes": ["R76", "C38", "H19", "F24", "U79", "D19", "P37", "Y39", "L39", "F28", "Q92"]}, "../public/img/sentinel/sentinel_68.jpg": {"correct_code": "D81", "coordinate": [282, 273], "correct_codes": ["U51", "J15", "D98", "B63", "U49", "D81", "U28", "E25", "J72", "N95"]}, "../public/img/sentinel/sentinel_69.jpg": {"correct_code": "K39", "coordinate": [1172, 428], "correct_codes": ["J27", "A82", "U53", "K39", "F23", "X45", "H91", "G96"]}, "../public/img/sentinel/sentinel_70.jpg": {"correct_code": "T91", "coordinate": [128, 281], "correct_codes": ["Z65", "T12", "T13", "R28", "T91", "V75", "N53", "Q49", "R48"]}, "../public/img/sentinel/sentinel_71.jpg": {"correct_code": "D38", "coordinate": [702, 224], "correct_codes": ["D25", "D15", "H32", "N61", "D34", "R56", "K38", "T39", "P61", "D38", "B89"]}, "../public/img/sentinel/sentinel_72.jpg": {"correct_code": "Y96", "coordinate": [1158, 131], "correct_codes": ["Y25", "W82", "L74", "B97", "F47", "J62", "Y96", "E28"]}, "../public/img/sentinel/sentinel_73.jpg": {"correct_code": "E56", "coordinate": [982, 388], "correct_codes": ["P47", "F45", "G35", "Y46", "Z28", "L37", "U95", "F83", "F62", "E56"]}, "../public/img/sentinel/sentinel_74.jpg": {"correct_code": "N58", "coordinate": [465, 508], "correct_codes": ["S71", "R72", "P34", "X46", "H34", "M36", "M63", "N58"]}, "../public/img/sentinel/sentinel_75.jpg": {"correct_code": "V23", "coordinate": [525, 386], "correct_codes": ["R58", "H41", "F15", "Y39", "K68", "R81", "J32", "V23", "Y21"]}, "../public/img/sentinel/sentinel_76.jpg": {"correct_code": "Y51", "coordinate": [932, 336], "correct_codes": ["H41", "T89", "V78", "V39", "W32", "C89", "K42", "Q96", "J28", "Y51"]}, "../public/img/sentinel/sentinel_77.jpg": {"correct_code": "A47", "coordinate": [516, 598], "correct_codes": ["P89", "A47", "J81", "H56", "A16", "R64", "R87", "Q59", "W15", "V26"]}, "../public/img/sentinel/sentinel_78.jpg": {"correct_code": "X49", "coordinate": [428, 591], "correct_codes": ["M71", "C53", "N61", "X49", "T69", "S65", "T26", "R47", "B24"]}, "../public/img/sentinel/sentinel_79.jpg": {"correct_code": "C19", "coordinate": [106, 427], "correct_codes": ["A15", "U97", "C42", "Y45", "S59", "V14", "X57", "U25", "C19"]}, "../public/img/sentinel/sentinel_80.jpg": {"correct_code": "J42", "coordinate": [279, 266], "correct_codes": ["X24", "J42", "S25", "W83", "M62", "C16", "V83", "T21", "H57", "J75"]}, "../public/img/sentinel/sentinel_81.jpg": {"correct_code": "L43", "coordinate": [676, 284], "correct_codes": ["X67", "L43", "F15", "S63", "T28", "A18", "S39", "R86", "N96", "P54"]}, "../public/img/sentinel/sentinel_82.jpg": {"correct_code": "N78", "coordinate": [923, 350], "correct_codes": ["T97", "G89", "Z62", "C23", "T63", "N78", "W63", "K18", "P93"]}, "../public/img/sentinel/sentinel_83.jpg": {"correct_code": "X81", "coordinate": [422, 586], "correct_codes": ["C29", "C36", "N39", "E64", "T47", "D12", "S85", "L59", "X81", "K57"]}, "../public/img/sentinel/sentinel_84.jpg": {"correct_code": "D51", "coordinate": [752, 499], "correct_codes": ["E87", "Z68", "B56", "D51", "D53", "P25", "B92", "G78", "H93", "F52", "M95"]}, "../public/img/sentinel/sentinel_85.jpg": {"correct_code": "M78", "coordinate": [174, 600], "correct_codes": ["W39", "Z85", "D51", "M78", "C82", "T17", "A58", "B42", "G62"]}, "../public/img/sentinel/sentinel_86.jpg": {"correct_code": "E91", "coordinate": [857, 387], "correct_codes": ["B79", "E91", "N13", "C54", "F94", "Q64", "L18", "R95", "E28", "F83", "D45"]}, "../public/img/sentinel/sentinel_87.jpg": {"correct_code": "W54", "coordinate": [1083, 222], "correct_codes": ["D52", "Q15", "Y34", "T96", "M67", "P84", "C67", "W18", "W54", "Z63"]}, "../public/img/sentinel/sentinel_88.jpg": {"correct_code": "G21", "coordinate": [919, 325], "correct_codes": ["H17", "B31", "G21", "U42", "E75", "V96", "J17", "S47", "Z19"]}, "../public/img/sentinel/sentinel_89.jpg": {"correct_code": "J92", "coordinate": [1028, 127], "correct_codes": ["Q57", "B98", "R85", "L49", "J92", "U64", "K16", "J85"]}, "../public/img/sentinel/sentinel_90.jpg": {"correct_code": "F31", "coordinate": [338, 229], "correct_codes": ["Y61", "G31", "L31", "F31", "G95", "Z81", "X72", "U62", "Z79"]}, "../public/img/sentinel/sentinel_91.jpg": {"correct_code": "P14", "coordinate": [689, 155], "correct_codes": ["B73", "G26", "Z67", "P69", "H25", "U96", "P14", "E65", "A56", "L37"]}, "../public/img/sentinel/sentinel_92.jpg": {"correct_code": "M21", "coordinate": [1028, 488], "correct_codes": ["X87", "U78", "M21", "T42", "E15", "D95", "E81", "C58", "L59", "R43"]}, "../public/img/sentinel/sentinel_93.jpg": {"correct_code": "Z13", "coordinate": [1173, 377], "correct_codes": ["D29", "J21", "W89", "T72", "K47", "D53", "P48", "Z13"]}, "../public/img/sentinel/sentinel_94.jpg": {"correct_code": "G71", "coordinate": [768, 433], "correct_codes": ["G57", "U96", "G71", "H94", "Z27", "A53", "Y96", "W15", "B83"]}, "../public/img/sentinel/sentinel_95.jpg": {"correct_code": "X24", "coordinate": [778, 498], "correct_codes": ["V43", "X24", "W86", "D51", "Z17", "C23", "N46", "Y14", "Y64", "A61", "T25"]}, "../public/img/sentinel/sentinel_96.jpg": {"correct_code": "P61", "coordinate": [106, 590], "correct_codes": ["T53", "X38", "Q85", "D97", "C41", "B91", "K46", "U63", "P61", "K25"]}, "../public/img/sentinel/sentinel_97.jpg": {"correct_code": "B63", "coordinate": [524, 248], "correct_codes": ["P75", "N65", "B63", "C73", "Q61", "A17", "V81", "G76", "Z31"]}, "../public/img/sentinel/sentinel_98.jpg": {"correct_code": "D24", "coordinate": [101, 125], "correct_codes": ["V61", "N24", "V56", "D24", "Q52", "E25", "B23", "N67", "T61", "V92"]}, "../public/img/sentinel/sentinel_99.jpg": {"correct_code": "F63", "coordinate": [502, 597], "correct_codes": ["K63", "A16", "H18", "H34", "H96", "V91", "Z63", "F63", "G62", "D45"]}, "../public/img/sentinel/sentinel_100.jpg": {"correct_code": "L17", "coordinate": [531, 299], "correct_codes": ["A65", "X54", "E98", "Y17", "G91", "M97", "K83", "T23", "M79", "Q58", "L17"]}, "../public/img/sentinel/sentinel_101.jpg": {"correct_code": "F39", "coordinate": [501, 545], "correct_codes": ["V27", "V34", "K94", "R38", "F39", "C17", "L19", "Y83"]}, "../public/img/sentinel/sentinel_102.jpg": {"correct_code": "F42", "coordinate": [830, 187], "correct_codes": ["G41", "S93", "W68", "F42", "Q53", "D84", "E57", "E56"]}, "../public/img/sentinel/sentinel_103.jpg": {"correct_code": "K26", "coordinate": [789, 388], "correct_codes": ["C53", "K26", "D79", "J98", "V91", "N45", "M64", "G68", "L15", "P54"]}, "../public/img/sentinel/sentinel_104.jpg": {"correct_code": "P34", "coordinate": [576, 490], "correct_codes": ["A74", "P34", "U57", "A21", "P24", "Q63", "G62"]}, "../public/img/sentinel/sentinel_105.jpg": {"correct_code": "M43", "coordinate": [942, 119], "correct_codes": ["S76", "L14", "Q36", "M12", "A98", "M43", "A23", "Y81", "T32", "F57"]}, "../public/img/sentinel/sentinel_106.jpg": {"correct_code": "G16", "coordinate": [454, 501], "correct_codes": ["S89", "F31", "N19", "S54", "G16", "T18", "K98", "D13", "Y98", "B24"]}, "../public/img/sentinel/sentinel_107.jpg": {"correct_code": "P49", "coordinate": [692, 434], "correct_codes": ["Z65", "R72", "P49", "F56", "Y79", "B86", "E54", "Y78", "V87", "L67", "E94"]}, "../public/img/sentinel/sentinel_108.jpg": {"correct_code": "E89", "coordinate": [597, 324], "correct_codes": ["D25", "N71", "V65", "N82", "R51", "E89", "R64", "B19", "C14", "Y67"]}, "../public/img/sentinel/sentinel_109.jpg": {"correct_code": "V84", "coordinate": [265, 563], "correct_codes": ["L98", "X65", "C25", "M38", "V49", "T96", "R19", "S81", "K14", "V84"]}, "../public/img/sentinel/sentinel_110.jpg": {"correct_code": "L54", "coordinate": [1019, 352], "correct_codes": ["W82", "H95", "K73", "V26", "F56", "Q35", "C48", "M47", "L54", "X14"]}, "../public/img/sentinel/sentinel_111.jpg": {"correct_code": "X46", "coordinate": [468, 338], "correct_codes": ["Y25", "U76", "L38", "Y85", "X46", "E63", "G86", "J49", "T95"]}, "../public/img/sentinel/sentinel_112.jpg": {"correct_code": "N64", "coordinate": [200, 376], "correct_codes": ["V63", "N64", "E23", "R29", "U96", "S57", "P82", "K37", "B17", "N89"]}, "../public/img/sentinel/sentinel_113.jpg": {"correct_code": "T47", "coordinate": [610, 554], "correct_codes": ["W87", "P49", "F54", "T91", "T47", "J68", "G32", "M76", "X91"]}, "../public/img/sentinel/sentinel_114.jpg": {"correct_code": "S94", "coordinate": [683, 173], "correct_codes": ["L96", "Y19", "Y86", "S94", "R85", "N67", "A96", "Q81", "M63", "G63"]}, "../public/img/sentinel/sentinel_115.jpg": {"correct_code": "K28", "coordinate": [692, 328], "correct_codes": ["W93", "K26", "E32", "G67", "J71", "X97", "F98", "P98", "K28"]}, "../public/img/sentinel/sentinel_116.jpg": {"correct_code": "E65", "coordinate": [1002, 483], "correct_codes": ["W85", "P53", "D27", "J65", "E65", "Q21", "T19", "W43", "R25"]}, "../public/img/sentinel/sentinel_117.jpg": {"correct_code": "V63", "coordinate": [157, 393], "correct_codes": ["V63", "T12", "P14", "B59", "R75", "K27", "X21"]}, "../public/img/sentinel/sentinel_118.jpg": {"correct_code": "V82", "coordinate": [255, 487], "correct_codes": ["W86", "M75", "V82", "C24", "P15", "Q61", "K42", "D39", "T41", "U68"]}, "../public/img/sentinel/sentinel_119.jpg": {"correct_code": "M97", "coordinate": [1141, 614], "correct_codes": ["J74", "H17", "D52", "Q37", "M97", "B52", "L69", "R64", "J49", "D93"]}, "../public/img/sentinel/sentinel_120.jpg": {"correct_code": "V59", "coordinate": [444, 171], "correct_codes": ["Q42", "U94", "C45", "V59", "J48", "S82", "S14", "D59", "C62", "Q41"]}, "../public/img/sentinel/sentinel_121.jpg": {"correct_code": "B16", "coordinate": [851, 276], "correct_codes": ["T13", "G18", "N98", "B18", "B54", "R14", "B16", "A95", "Q12", "H57"]}, "../public/img/sentinel/sentinel_122.jpg": {"correct_code": "P45", "coordinate": [133, 488], "correct_codes": ["L87", "P45", "V48", "G75", "M91", "U96", "U53", "A71"]}, "../public/img/sentinel/sentinel_123.jpg": {"correct_code": "M63", "coordinate": [684, 554], "correct_codes": ["L96", "R83", "M97", "K49", "A54", "Q63", "M63", "Q17", "Y29", "G29"]}, "../public/img/sentinel/sentinel_124.jpg": {"correct_code": "F49", "coordinate": [854, 442], "correct_codes": ["R35", "W87", "Z86", "W62", "D19", "S72", "R79", "G68", "F49"]}, "../public/img/sentinel/sentinel_125.jpg": {"correct_code": "R86", "coordinate": [822, 189], "correct_codes": ["Y62", "T43", "U67", "B49", "E12", "H53", "Z47", "R86", "S42", "H45"]}, "../public/img/sentinel/sentinel_126.jpg": {"correct_code": "K41", "coordinate": [111, 460], "correct_codes": ["R72", "U49", "Z15", "J95", "B38", "X84", "N52", "A27", "K41", "G37", "F38"]}, "../public/img/sentinel/sentinel_127.jpg": {"correct_code": "Z97", "coordinate": [1083, 455], "correct_codes": ["Z97", "E43", "X49", "R97", "T82", "U25", "Y71", "H84", "F52", "M93"]}, "../public/img/sentinel/sentinel_128.jpg": {"correct_code": "Z15", "coordinate": [919, 528], "correct_codes": ["Y36", "Z15", "C36", "X68", "K52", "J97", "K13", "T86", "Z27", "U68"]}, "../public/img/sentinel/sentinel_129.jpg": {"correct_code": "R28", "coordinate": [283, 238], "correct_codes": ["W92", "S71", "R28", "Y89", "B12", "K32", "G29", "E68", "N58"]}, "../public/img/sentinel/sentinel_130.jpg": {"correct_code": "S83", "coordinate": [414, 609], "correct_codes": ["S83", "K43", "T54", "P76", "H19", "A38", "B36", "J45", "C43"]}, "../public/img/sentinel/sentinel_131.jpg": {"correct_code": "H43", "coordinate": [1114, 548], "correct_codes": ["H43", "A65", "U71", "S28", "V93", "V78", "X27", "F12", "T41", "Y71", "R95"]}, "../public/img/sentinel/sentinel_132.jpg": {"correct_code": "L25", "coordinate": [1085, 130], "correct_codes": ["V27", "Q98", "Z16", "L25", "R94", "S43", "F78", "U84", "K97", "P65"]}, "../public/img/sentinel/sentinel_133.jpg": {"correct_code": "V64", "coordinate": [1161, 328], "correct_codes": ["W79", "Y12", "L23", "V64", "Z36", "B58", "G37"]}, "../public/img/sentinel/sentinel_134.jpg": {"correct_code": "T69", "coordinate": [166, 392], "correct_codes": ["W64", "T83", "E86", "S82", "N57", "T69", "M84", "N43", "C58", "J87"]}, "../public/img/sentinel/sentinel_135.jpg": {"correct_code": "P28", "coordinate": [177, 105], "correct_codes": ["G46", "P28", "Y94", "Z85", "J97", "V83", "G74", "K18", "K81"]}, "../public/img/sentinel/sentinel_136.jpg": {"correct_code": "A32", "coordinate": [420, 320], "correct_codes": ["K69", "Z53", "A32", "K46", "F23", "E39", "S39", "B78", "X93", "E59", "U61"]}, "../public/img/sentinel/sentinel_137.jpg": {"correct_code": "W58", "coordinate": [251, 550], "correct_codes": ["W58", "F35", "N27", "G15", "W12", "L19", "M17", "K24", "L92"]}, "../public/img/sentinel/sentinel_138.jpg": {"correct_code": "P29", "coordinate": [452, 243], "correct_codes": ["P29", "D54", "M72", "L53", "P15", "J97", "V94", "G82", "M69", "Z46"]}, "../public/img/sentinel/sentinel_139.jpg": {"correct_code": "X75", "coordinate": [600, 128], "correct_codes": ["A15", "Q51", "R72", "J81", "V78", "X75", "H92", "X45", "Z24", "V74"]}, "../public/img/sentinel/sentinel_140.jpg": {"correct_code": "Z18", "coordinate": [413, 541], "correct_codes": ["X12", "C36", "H16", "J73", "T65", "K12", "R17", "Z18", "F74"]}, "../public/img/sentinel/sentinel_141.jpg": {"correct_code": "Y75", "coordinate": [1023, 167], "correct_codes": ["V27", "U56", "T54", "A89", "H19", "Y75", "C87", "E32", "G54", "U19", "Q81"]}, "../public/img/sentinel/sentinel_142.jpg": {"correct_code": "U83", "coordinate": [625, 493], "correct_codes": ["G51", "F95", "V62", "B95", "R97", "J17", "X91", "U83", "A64", "G53"]}, "../public/img/sentinel/sentinel_143.jpg": {"correct_code": "Q68", "coordinate": [353, 172], "correct_codes": ["Y41", "S74", "A32", "Q68", "H98", "W37", "J72", "E85", "F53", "Q31"]}, "../public/img/sentinel/sentinel_144.jpg": {"correct_code": "P61", "coordinate": [435, 442], "correct_codes": ["Q69", "C39", "N91", "J27", "Z29", "K53", "N73", "F23", "P61", "M28", "Y37"]}, "../public/img/sentinel/sentinel_145.jpg": {"correct_code": "C76", "coordinate": [1087, 342], "correct_codes": ["C76", "U65", "Y27", "E32", "B14", "X64", "L86", "C19", "Y83", "V42"]}, "../public/img/sentinel/sentinel_146.jpg": {"correct_code": "M79", "coordinate": [818, 601], "correct_codes": ["Z51", "Y35", "Q14", "D26", "N41", "D23", "X51", "M79", "T15", "V38"]}, "../public/img/sentinel/sentinel_147.jpg": {"correct_code": "M62", "coordinate": [674, 395], "correct_codes": ["P97", "R68", "R46", "G61", "M81", "V73", "M62", "N72", "L67", "G62"]}, "../public/img/sentinel/sentinel_148.jpg": {"correct_code": "S84", "coordinate": [1077, 549], "correct_codes": ["P76", "G56", "Q73", "E65", "Z56", "B58", "Z82", "H28", "F83", "S84"]}, "../public/img/sentinel/sentinel_149.jpg": {"correct_code": "Q81", "coordinate": [1028, 110], "correct_codes": ["T57", "F24", "B15", "A82", "V54", "V86", "J49", "Q81", "H28"]}, "../public/img/sentinel/sentinel_150.jpg": {"correct_code": "H72", "coordinate": [926, 332], "correct_codes": ["H72", "D36", "S61", "H53", "W51", "R43", "J85"]}, "../public/img/sentinel/sentinel_151.jpg": {"correct_code": "V94", "coordinate": [1085, 287], "correct_codes": ["V51", "X74", "D49", "V94", "K72", "V92", "Q76", "V53", "V26"]}, "../public/img/sentinel/sentinel_152.jpg": {"correct_code": "F59", "coordinate": [186, 400], "correct_codes": ["Y68", "D52", "S87", "F59", "E91", "U35", "T82", "L17", "K81", "C93"]}, "../public/img/sentinel/sentinel_153.jpg": {"correct_code": "E38", "coordinate": [1161, 596], "correct_codes": ["E38", "H83", "K71", "A21", "V32", "K56", "N96"]}, "../public/img/sentinel/sentinel_154.jpg": {"correct_code": "Y62", "coordinate": [350, 539], "correct_codes": ["X24", "L14", "H41", "Y62", "M39", "T34", "A56", "C71", "V71", "V95", "Y18"]}, "../public/img/sentinel/sentinel_155.jpg": {"correct_code": "V68", "coordinate": [1165, 277], "correct_codes": ["V68", "U56", "Q87", "Y32", "D54", "M83", "V32"]}, "../public/img/sentinel/sentinel_156.jpg": {"correct_code": "F46", "coordinate": [170, 592], "correct_codes": ["J74", "F46", "G31", "Y58", "E46", "E12", "G92", "T14", "J24", "Q31"]}, "../public/img/sentinel/sentinel_157.jpg": {"correct_code": "W86", "coordinate": [360, 293], "correct_codes": ["W86", "C98", "C91", "R18", "N12", "K32", "T38", "Q48", "J76"]}, "../public/img/sentinel/sentinel_158.jpg": {"correct_code": "U63", "coordinate": [1177, 474], "correct_codes": ["W16", "X87", "Y59", "F84", "C82", "U63", "Z24"]}, "../public/img/sentinel/sentinel_159.jpg": {"correct_code": "B34", "coordinate": [272, 558], "correct_codes": ["B34", "P35", "V86", "G95", "T86", "B14", "E39", "Q97", "A53", "L46"]}, "../public/img/sentinel/sentinel_160.jpg": {"correct_code": "C87", "coordinate": [125, 192], "correct_codes": ["L96", "U85", "Y79", "F13", "J36", "C87", "D39", "E62", "W15"]}, "../public/img/sentinel/sentinel_161.jpg": {"correct_code": "N28", "coordinate": [414, 566], "correct_codes": ["B25", "Z49", "C87", "N81", "H79", "D48", "D12", "X97", "N28"]}, "../public/img/sentinel/sentinel_162.jpg": {"correct_code": "Q17", "coordinate": [854, 182], "correct_codes": ["T97", "E93", "H64", "E32", "L73", "Z78", "E69", "L36", "H27", "Q17", "Z13"]}, "../public/img/sentinel/sentinel_163.jpg": {"correct_code": "D32", "coordinate": [349, 225], "correct_codes": ["K87", "T71", "W81", "V15", "A21", "F93", "N37", "V97", "D32", "Y84"]}, "../public/img/sentinel/sentinel_164.jpg": {"correct_code": "D78", "coordinate": [421, 406], "correct_codes": ["W16", "G38", "D78", "D54", "H19", "X89", "M43", "Z91", "Y14", "V32"]}, "../public/img/sentinel/sentinel_165.jpg": {"correct_code": "E13", "coordinate": [1007, 132], "correct_codes": ["S25", "Z23", "W78", "E13", "L47", "M84", "R14", "G12", "F83", "Y37"]}, "../public/img/sentinel/sentinel_166.jpg": {"correct_code": "P24", "coordinate": [523, 350], "correct_codes": ["L43", "D16", "R26", "E43", "W37", "S85", "L32", "P24", "H45"]}, "../public/img/sentinel/sentinel_167.jpg": {"correct_code": "T96", "coordinate": [199, 550], "correct_codes": ["B45", "F73", "J47", "C28", "T96", "B86", "Z21", "F87", "M76", "Y23"]}, "../public/img/sentinel/sentinel_168.jpg": {"correct_code": "V58", "coordinate": [1003, 559], "correct_codes": ["W32", "V58", "D23", "N95", "A59", "X92", "D32", "X21", "R47"]}, "../public/img/sentinel/sentinel_169.jpg": {"correct_code": "T23", "coordinate": [527, 226], "correct_codes": ["Y68", "Y86", "N85", "B56", "T23", "N95", "Z36", "A58", "K48", "H91"]}, "../public/img/sentinel/sentinel_170.jpg": {"correct_code": "C76", "coordinate": [373, 276], "correct_codes": ["H78", "H72", "M52", "C76", "F75", "T78", "Q27", "B23"]}, "../public/img/sentinel/sentinel_171.jpg": {"correct_code": "E68", "coordinate": [847, 342], "correct_codes": ["Y68", "X59", "H46", "L53", "V65", "Z34", "E63", "N52", "G49", "E68"]}, "../public/img/sentinel/sentinel_172.jpg": {"correct_code": "D71", "coordinate": [931, 554], "correct_codes": ["H97", "J35", "N93", "H24", "G58", "F69", "B38", "V31", "A92", "D71"]}, "../public/img/sentinel/sentinel_173.jpg": {"correct_code": "T71", "coordinate": [603, 227], "correct_codes": ["T71", "C53", "J36", "E43", "L59", "A95", "D62", "R13", "X93"]}, "../public/img/sentinel/sentinel_174.jpg": {"correct_code": "N98", "coordinate": [201, 503], "correct_codes": ["J26", "E87", "H14", "J52", "D15", "N98", "W73", "U72", "X96", "X19", "P98"]}, "../public/img/sentinel/sentinel_175.jpg": {"correct_code": "W25", "coordinate": [422, 292], "correct_codes": ["W27", "F14", "H97", "J48", "V39", "A82", "W25", "H15", "Y67"]}, "../public/img/sentinel/sentinel_176.jpg": {"correct_code": "B53", "coordinate": [1157, 536], "correct_codes": ["B26", "G31", "G97", "B53", "K39", "T61", "V29", "H84"]}, "../public/img/sentinel/sentinel_177.jpg": {"correct_code": "A59", "coordinate": [926, 606], "correct_codes": ["F45", "H89", "R45", "K34", "Q83", "H83", "X96", "A59", "W14", "K21"]}, "../public/img/sentinel/sentinel_178.jpg": {"correct_code": "U63", "coordinate": [1003, 432], "correct_codes": ["Y68", "N69", "D78", "J57", "H64", "X49", "W26", "N78", "U63", "B78"]}, "../public/img/sentinel/sentinel_179.jpg": {"correct_code": "D38", "coordinate": [1005, 185], "correct_codes": ["V28", "H59", "G34", "W68", "R26", "M74", "X46", "M26", "K49", "U84", "D38"]}, "../public/img/sentinel/sentinel_180.jpg": {"correct_code": "K42", "coordinate": [772, 160], "correct_codes": ["W81", "P38", "K42", "R78", "F21", "K46", "Y57", "L37", "S35"]}, "../public/img/sentinel/sentinel_181.jpg": {"correct_code": "X98", "coordinate": [207, 490], "correct_codes": ["T16", "H71", "X98", "X49", "V96", "C81", "F87", "K56", "Z27", "U52"]}, "../public/img/sentinel/sentinel_182.jpg": {"correct_code": "Q98", "coordinate": [112, 480], "correct_codes": ["V28", "Q98", "V59", "G18", "D49", "N64", "R97", "W73", "P81"]}, "../public/img/sentinel/sentinel_183.jpg": {"correct_code": "V13", "coordinate": [773, 600], "correct_codes": ["W27", "N76", "V13", "P16", "X68", "X16", "C64", "K37", "Z13", "F57"]}, "../public/img/sentinel/sentinel_184.jpg": {"correct_code": "J25", "coordinate": [850, 122], "correct_codes": ["T52", "J25", "M54", "T43", "A79", "K54", "U46", "L86"]}, "../public/img/sentinel/sentinel_185.jpg": {"correct_code": "H46", "coordinate": [1090, 121], "correct_codes": ["H46", "V13", "W29", "Z68", "S97", "A18", "X81", "U46", "H21"]}, "../public/img/sentinel/sentinel_186.jpg": {"correct_code": "R52", "coordinate": [1004, 270], "correct_codes": ["U71", "G41", "S91", "P57", "W83", "V41", "R52", "B19", "Q13", "J41", "G79"]}, "../public/img/sentinel/sentinel_187.jpg": {"correct_code": "B81", "coordinate": [367, 319], "correct_codes": ["Q57", "U29", "N93", "U86", "B81", "N35", "K37", "G83", "T87"]}, "../public/img/sentinel/sentinel_188.jpg": {"correct_code": "G62", "coordinate": [1067, 132], "correct_codes": ["J21", "Z25", "E86", "E75", "E54", "M86", "N78", "G62", "W96"]}, "../public/img/sentinel/sentinel_189.jpg": {"correct_code": "S83", "coordinate": [181, 422], "correct_codes": ["S83", "T93", "T71", "F64", "W81", "L13", "H82", "L51", "M32", "H57", "J64"]}, "../public/img/sentinel/sentinel_190.jpg": {"correct_code": "Z25", "coordinate": [1122, 392], "correct_codes": ["W47", "R71", "Z25", "N85", "V14", "L68", "J16", "Q38", "Q59", "N89"]}, "../public/img/sentinel/sentinel_191.jpg": {"correct_code": "X31", "coordinate": [455, 175], "correct_codes": ["X79", "X38", "R94", "P67", "L89", "P13", "N92", "X31", "G74"]}, "../public/img/sentinel/sentinel_192.jpg": {"correct_code": "D98", "coordinate": [106, 498], "correct_codes": ["D98", "Y36", "V48", "X72", "B94", "Y39", "D86", "Y14", "A14", "W96"]}, "../public/img/sentinel/sentinel_193.jpg": {"correct_code": "F84", "coordinate": [1146, 460], "correct_codes": ["N18", "V63", "F84", "Z37", "U62", "Y78", "A68"]}, "../public/img/sentinel/sentinel_194.jpg": {"correct_code": "L45", "coordinate": [532, 231], "correct_codes": ["B51", "P83", "J82", "X63", "L45", "Z24", "J16", "P56", "H23", "K19", "N25"]}, "../public/img/sentinel/sentinel_195.jpg": {"correct_code": "N96", "coordinate": [186, 173], "correct_codes": ["S83", "A38", "M27", "X16", "B21", "H21", "Q17", "N96", "M35"]}, "../public/img/sentinel/sentinel_196.jpg": {"correct_code": "D97", "coordinate": [1170, 128], "correct_codes": ["W86", "D97", "R92", "M84", "S98", "D21", "T98"]}, "../public/img/sentinel/sentinel_197.jpg": {"correct_code": "S57", "coordinate": [105, 374], "correct_codes": ["B73", "B31", "D85", "T47", "M43", "W13", "B93", "S57", "P65", "G65"]}, "../public/img/sentinel/sentinel_198.jpg": {"correct_code": "Y81", "coordinate": [837, 113], "correct_codes": ["C42", "L76", "S27", "U84", "M17", "Q32", "Q96", "E85", "Y81", "X25"]}, "../public/img/sentinel/sentinel_199.jpg": {"correct_code": "C13", "coordinate": [255, 221], "correct_codes": ["G34", "Z45", "G31", "Q78", "D27", "E45", "X34", "C13", "V57", "D18"]}, "../public/img/sentinel/sentinel_200.jpg": {"correct_code": "S31", "coordinate": [850, 281], "correct_codes": ["U81", "V78", "S31", "X75", "V75", "Z34", "Q43", "T63", "Z56", "R89", "W46", "P54"]}, "../public/img/sentinel/sentinel_201.jpg": {"correct_code": "K12", "coordinate": [926, 332], "correct_codes": ["M75", "R72", "N26", "T51", "B53", "K12", "R81", "F74", "T29"]}, "../public/img/sentinel/sentinel_202.jpg": {"correct_code": "A73", "coordinate": [748, 338], "correct_codes": ["Y68", "F56", "T37", "V57", "E83", "T79", "A73", "V53", "E18"]}, "../public/img/sentinel/sentinel_203.jpg": {"correct_code": "B32", "coordinate": [591, 608], "correct_codes": ["X38", "A13", "B32", "Q35", "X56", "D95", "B58", "Z58"]}, "../public/img/sentinel/sentinel_204.jpg": {"correct_code": "A72", "coordinate": [450, 124], "correct_codes": ["A15", "Q47", "A72", "K63", "C89", "J43", "D21", "S45", "Z58"]}, "../public/img/sentinel/sentinel_205.jpg": {"correct_code": "Z71", "coordinate": [421, 392], "correct_codes": ["D37", "W47", "Y73", "Z64", "S74", "C62", "A38", "W61", "Z71", "D75", "V91"]}, "../public/img/sentinel/sentinel_206.jpg": {"correct_code": "H57", "coordinate": [1003, 224], "correct_codes": ["W82", "N16", "X57", "G17", "B54", "R93", "H27", "Q81", "H57", "B85", "X36"]}, "../public/img/sentinel/sentinel_207.jpg": {"correct_code": "W46", "coordinate": [258, 395], "correct_codes": ["L74", "D81", "S59", "F65", "J96", "K42", "F84", "F12", "W46", "F32"]}, "../public/img/sentinel/sentinel_208.jpg": {"correct_code": "X32", "coordinate": [1070, 298], "correct_codes": ["Q42", "W58", "P46", "P45", "C76", "F54", "J86", "C16", "X32", "Q48"]}, "../public/img/sentinel/sentinel_209.jpg": {"correct_code": "C45", "coordinate": [439, 223], "correct_codes": ["Y68", "D78", "C45", "J84", "K72", "T85", "T73", "C47", "U98", "G79"]}, "../public/img/sentinel/sentinel_210.jpg": {"correct_code": "Z35", "coordinate": [686, 530], "correct_codes": ["F25", "L87", "Z35", "T89", "S67", "H64", "Q37", "J46", "X84"]}, "../public/img/sentinel/sentinel_211.jpg": {"correct_code": "R85", "coordinate": [1092, 397], "correct_codes": ["B39", "V68", "J52", "C73", "P53", "V98", "R85", "S81", "P24", "Z42"]}, "../public/img/sentinel/sentinel_212.jpg": {"correct_code": "Q38", "coordinate": [1165, 194], "correct_codes": ["H48", "B15", "Z17", "N57", "Q38", "W24"]}, "../public/img/sentinel/sentinel_213.jpg": {"correct_code": "E19", "coordinate": [770, 441], "correct_codes": ["M46", "C52", "R18", "U41", "Q37", "E19", "K92", "G79"]}, "../public/img/sentinel/sentinel_214.jpg": {"correct_code": "H31", "coordinate": [348, 505], "correct_codes": ["B39", "Y47", "D37", "Y54", "P47", "B69", "W29", "G15", "D87", "H31", "V38"]}, "../public/img/sentinel/sentinel_215.jpg": {"correct_code": "W23", "coordinate": [861, 292], "correct_codes": ["W23", "X18", "L53", "M54", "Y41", "C21", "D24", "N86", "Q92"]}, "../public/img/sentinel/sentinel_216.jpg": {"correct_code": "D27", "coordinate": [941, 566], "correct_codes": ["L42", "N63", "N27", "Y41", "D27", "V86", "M84", "X52", "M89"]}, "../public/img/sentinel/sentinel_217.jpg": {"correct_code": "M52", "coordinate": [686, 355], "correct_codes": ["M52", "J23", "F21", "E65", "K82", "C78", "L92", "C56", "E47", "U12"]}, "../public/img/sentinel/sentinel_218.jpg": {"correct_code": "X59", "coordinate": [996, 605], "correct_codes": ["X59", "X35", "F84", "B49", "S38", "G49", "S26", "P58", "J85"]}, "../public/img/sentinel/sentinel_219.jpg": {"correct_code": "S92", "coordinate": [219, 273], "correct_codes": ["S92", "G46", "Z26", "U78", "S13", "P72", "C13", "S69"]}, "../public/img/sentinel/sentinel_220.jpg": {"correct_code": "F42", "coordinate": [194, 605], "correct_codes": ["N69", "D72", "X41", "R53", "F42", "C17", "X51", "T35", "U34"]}, "../public/img/sentinel/sentinel_221.jpg": {"correct_code": "G87", "coordinate": [1088, 175], "correct_codes": ["V43", "V79", "G87", "P31", "W31", "U82", "E48", "B53", "M94", "P92", "R25"]}, "../public/img/sentinel/sentinel_222.jpg": {"correct_code": "S58", "coordinate": [622, 496], "correct_codes": ["E41", "A13", "S58", "S87", "Q32", "A53", "Q81", "G65", "X83"]}, "../public/img/sentinel/sentinel_223.jpg": {"correct_code": "Q18", "coordinate": [422, 350], "correct_codes": ["D37", "Z65", "D61", "K67", "Q18", "J61", "P82", "C26", "H84", "M92"]}, "../public/img/sentinel/sentinel_224.jpg": {"correct_code": "N29", "coordinate": [599, 395], "correct_codes": ["A69", "T71", "S25", "A47", "G24", "H61", "W13", "X14", "N29", "G85"]}, "../public/img/sentinel/sentinel_225.jpg": {"correct_code": "M39", "coordinate": [781, 183], "correct_codes": ["V37", "T52", "E98", "L56", "C32", "Z49", "S43", "K95", "M39", "M57"]}, "../public/img/sentinel/sentinel_226.jpg": {"correct_code": "G41", "coordinate": [281, 235], "correct_codes": ["G41", "C94", "P23", "P53", "Y46", "B91", "V29", "L65", "G23"]}, "../public/img/sentinel/sentinel_227.jpg": {"correct_code": "T73", "coordinate": [416, 186], "correct_codes": ["Z95", "W69", "J84", "M25", "A26", "N19", "X47", "X31", "T73", "T79", "J87"]}, "../public/img/sentinel/sentinel_228.jpg": {"correct_code": "L19", "coordinate": [772, 441], "correct_codes": ["T93", "G97", "B15", "L19", "N92", "A27", "S78", "X92", "S45", "R47"]}, "../public/img/sentinel/sentinel_229.jpg": {"correct_code": "B28", "coordinate": [334, 229], "correct_codes": ["B28", "S94", "V96", "V81", "J19", "E26", "P85", "L39", "V26"]}, "../public/img/sentinel/sentinel_230.jpg": {"correct_code": "N38", "coordinate": [608, 446], "correct_codes": ["Y97", "L14", "W72", "S58", "S12", "Q72", "G95", "N68", "N38", "G32"]}, "../public/img/sentinel/sentinel_231.jpg": {"correct_code": "V85", "coordinate": [1094, 176], "correct_codes": ["C38", "P74", "N85", "P34", "D17", "K26", "H83", "A92", "V85", "C69"]}, "../public/img/sentinel/sentinel_232.jpg": {"correct_code": "U12", "coordinate": [603, 613], "correct_codes": ["H43", "N69", "X65", "J86", "Z81", "Y27", "S52", "E92", "U12"]}, "../public/img/sentinel/sentinel_233.jpg": {"correct_code": "C89", "coordinate": [434, 166], "correct_codes": ["B65", "C89", "J27", "P83", "H81", "M97", "X52", "N45", "V23", "Y31"]}, "../public/img/sentinel/sentinel_234.jpg": {"correct_code": "Q76", "coordinate": [1010, 232], "correct_codes": ["Q75", "E38", "V37", "J95", "N86", "M43", "C96", "Q76", "H63", "M64"]}, "../public/img/sentinel/sentinel_235.jpg": {"correct_code": "L45", "coordinate": [848, 225], "correct_codes": ["V61", "Z35", "G45", "V59", "H34", "L45", "Z79", "Q67", "K48", "S37"]}, "../public/img/sentinel/sentinel_236.jpg": {"correct_code": "Y42", "coordinate": [328, 218], "correct_codes": ["M75", "S92", "F73", "F37", "V75", "L54", "L32", "H86", "Y42"]}, "../public/img/sentinel/sentinel_237.jpg": {"correct_code": "N89", "coordinate": [360, 492], "correct_codes": ["G46", "K69", "N71", "R21", "D61", "H25", "X57", "B81", "F96", "N89"]}, "../public/img/sentinel/sentinel_238.jpg": {"correct_code": "U26", "coordinate": [351, 130], "correct_codes": ["N31", "E98", "M41", "H35", "K39", "F72", "N12", "A27", "U26", "G53"]}, "../public/img/sentinel/sentinel_239.jpg": {"correct_code": "C52", "coordinate": [346, 235], "correct_codes": ["S73", "C52", "J96", "A36", "V64", "D84", "H15", "V35", "B37", "U37"]}, "../public/img/sentinel/sentinel_240.jpg": {"correct_code": "N14", "coordinate": [203, 481], "correct_codes": ["N14", "Y75", "R29", "Y63", "L23", "K14", "H69", "X91", "F96", "A64"]}, "../public/img/sentinel/sentinel_241.jpg": {"correct_code": "Y72", "coordinate": [270, 441], "correct_codes": ["Y19", "L74", "Y72", "E86", "C91", "F17", "N41", "G54", "L62", "Y18"]}, "../public/img/sentinel/sentinel_242.jpg": {"correct_code": "W28", "coordinate": [361, 118], "correct_codes": ["H48", "W47", "F65", "H35", "H67", "F78", "S49", "Y24", "W28", "Y48"]}, "../public/img/sentinel/sentinel_243.jpg": {"correct_code": "U38", "coordinate": [755, 186], "correct_codes": ["U38", "C29", "X76", "V56", "R51", "F19", "A59", "P41", "L85"]}, "../public/img/sentinel/sentinel_244.jpg": {"correct_code": "L87", "coordinate": [1009, 445], "correct_codes": ["V43", "U51", "L87", "Z45", "B41", "G64", "H39", "X83", "J24", "X95"]}, "../public/img/sentinel/sentinel_245.jpg": {"correct_code": "T75", "coordinate": [1121, 378], "correct_codes": ["H54", "W23", "Z95", "T75", "P42", "Q35", "N95", "E74", "N15"]}, "../public/img/sentinel/sentinel_246.jpg": {"correct_code": "Y83", "coordinate": [826, 584], "correct_codes": ["F46", "W89", "Z39", "H87", "Q21", "T46", "G73", "Y83", "T29"]}, "../public/img/sentinel/sentinel_247.jpg": {"correct_code": "Z17", "coordinate": [1017, 124], "correct_codes": ["H78", "V59", "N39", "M48", "G13", "Z17", "U19", "U84", "R15", "H49"]}, "../public/img/sentinel/sentinel_248.jpg": {"correct_code": "B98", "coordinate": [785, 400], "correct_codes": ["A74", "G51", "B98", "Y75", "H47", "T37", "W61", "G69", "Q84", "C19"]}, "../public/img/sentinel/sentinel_249.jpg": {"correct_code": "W71", "coordinate": [462, 603], "correct_codes": ["Z14", "T49", "Q85", "R52", "J46", "W71", "Q32", "K75", "V26"]}, "../public/img/sentinel/sentinel_250.jpg": {"correct_code": "E39", "coordinate": [527, 242], "correct_codes": ["N24", "V15", "P42", "H82", "G95", "U28", "Z79", "E39", "F58", "B74", "C67"]}, "../public/img/sentinel/sentinel_251.jpg": {"correct_code": "G16", "coordinate": [346, 126], "correct_codes": ["V28", "J59", "P12", "B56", "U65", "G16", "P25", "T35", "V97"]}, "../public/img/sentinel/sentinel_252.jpg": {"correct_code": "B39", "coordinate": [216, 504], "correct_codes": ["B39", "U71", "L98", "S16", "Y45", "A24", "Q53", "S57", "C71", "N89"]}, "../public/img/sentinel/sentinel_253.jpg": {"correct_code": "N13", "coordinate": [945, 553], "correct_codes": ["L96", "F82", "N32", "J97", "G48", "N13", "A21", "B16", "W28", "S75", "P81"]}, "../public/img/sentinel/sentinel_254.jpg": {"correct_code": "B57", "coordinate": [422, 457], "correct_codes": ["H38", "M14", "W81", "N61", "Q72", "U69", "M37", "D86", "G85", "B57"]}, "../public/img/sentinel/sentinel_255.jpg": {"correct_code": "U41", "coordinate": [1019, 598], "correct_codes": ["U29", "B73", "H41", "L75", "Y62", "T84", "U41", "L23", "N43", "S19"]}, "../public/img/sentinel/sentinel_256.jpg": {"correct_code": "G85", "coordinate": [437, 387], "correct_codes": ["P63", "P32", "R72", "E82", "D17", "Z81", "Y76", "G49", "G85"]}, "../public/img/sentinel/sentinel_257.jpg": {"correct_code": "K36", "coordinate": [1094, 136], "correct_codes": ["P49", "T78", "H16", "K36", "U27", "D48", "Y64", "Q91", "Z46", "X91"]}, "../public/img/sentinel/sentinel_258.jpg": {"correct_code": "B75", "coordinate": [1100, 219], "correct_codes": ["R41", "E79", "X42", "G27", "C32", "W93", "B75", "M89", "C95", "U32"]}, "../public/img/sentinel/sentinel_259.jpg": {"correct_code": "L67", "coordinate": [525, 334], "correct_codes": ["T75", "S13", "E75", "K83", "Y52", "Z56", "D65", "L67"]}, "../public/img/sentinel/sentinel_260.jpg": {"correct_code": "E23", "coordinate": [606, 181], "correct_codes": ["X54", "U93", "Q89", "K51", "E23", "E65", "T23", "Y24", "K97", "F89"]}, "../public/img/sentinel/sentinel_261.jpg": {"correct_code": "S14", "coordinate": [1081, 379], "correct_codes": ["M49", "P18", "X73", "S14", "N13", "P13", "Z36", "A68", "E74", "B67"]}, "../public/img/sentinel/sentinel_262.jpg": {"correct_code": "W39", "coordinate": [508, 224], "correct_codes": ["W39", "V51", "Z25", "V58", "X46", "S97", "T34", "A18", "N46", "S34"]}, "../public/img/sentinel/sentinel_263.jpg": {"correct_code": "K63", "coordinate": [183, 293], "correct_codes": ["X61", "K87", "H72", "K63", "U41", "F85", "T69", "M19", "C78", "Y23"]}, "../public/img/sentinel/sentinel_264.jpg": {"correct_code": "J95", "coordinate": [663, 599], "correct_codes": ["G57", "Q47", "J95", "S59", "C87", "R74", "T94", "L34", "V25", "L86"]}, "../public/img/sentinel/sentinel_265.jpg": {"correct_code": "F42", "coordinate": [1111, 408], "correct_codes": ["H95", "C74", "U42", "F42", "E53", "C82", "B54", "H49", "V42", "U37"]}, "../public/img/sentinel/sentinel_266.jpg": {"correct_code": "E46", "coordinate": [549, 195], "correct_codes": ["E71", "U96", "E45", "G48", "E46", "E63", "Z38", "S72", "R89"]}, "../public/img/sentinel/sentinel_267.jpg": {"correct_code": "U68", "coordinate": [862, 426], "correct_codes": ["X61", "X94", "Q89", "G35", "G89", "S13", "L46", "U68", "N58"]}, "../public/img/sentinel/sentinel_268.jpg": {"correct_code": "G93", "coordinate": [770, 561], "correct_codes": ["C42", "L48", "Y86", "E23", "M38", "T36", "Y27", "J61", "G93", "K93"]}, "../public/img/sentinel/sentinel_269.jpg": {"correct_code": "P76", "coordinate": [111, 324], "correct_codes": ["P76", "W47", "Y59", "Z64", "S15", "R94", "N82", "Z87", "F63", "U37"]}, "../public/img/sentinel/sentinel_270.jpg": {"correct_code": "F38", "coordinate": [854, 545], "correct_codes": ["J74", "S32", "E87", "V82", "N75", "M54", "P34", "G19", "F38"]}, "../public/img/sentinel/sentinel_271.jpg": {"correct_code": "W64", "coordinate": [120, 183], "correct_codes": ["V79", "A25", "W64", "Z97", "J46", "S27", "B23", "J89", "V74"]}, "../public/img/sentinel/sentinel_272.jpg": {"correct_code": "H31", "coordinate": [601, 110], "correct_codes": ["J15", "H19", "N14", "C87", "H31", "A83", "R69", "S51", "C14", "Y21"]}, "../public/img/sentinel/sentinel_273.jpg": {"correct_code": "H61", "coordinate": [422, 440], "correct_codes": ["S24", "X69", "J86", "S12", "D43", "H61", "J16", "W74", "M64"]}, "../public/img/sentinel/sentinel_274.jpg": {"correct_code": "S87", "coordinate": [269, 281], "correct_codes": ["L72", "L38", "E97", "S87", "Q79", "Y24", "A96", "U72", "B42"]}, "../public/img/sentinel/sentinel_275.jpg": {"correct_code": "N83", "coordinate": [941, 397], "correct_codes": ["Q87", "L56", "K63", "H92", "Y75", "N34", "N83", "R19", "S27", "T34", "J87"]}, "../public/img/sentinel/sentinel_276.jpg": {"correct_code": "A98", "coordinate": [1021, 298], "correct_codes": ["R41", "L96", "D37", "X65", "W29", "A98", "K36", "R62", "Z56", "J54", "F74"]}, "../public/img/sentinel/sentinel_277.jpg": {"correct_code": "W23", "coordinate": [289, 540], "correct_codes": ["W23", "J14", "H72", "J78", "P42", "S61", "E84", "Y63", "L34", "T82", "Q59"]}, "../public/img/sentinel/sentinel_278.jpg": {"correct_code": "Q49", "coordinate": [1159, 492], "correct_codes": ["X61", "N91", "N36", "G48", "U61", "Q49", "T25"]}, "../public/img/sentinel/sentinel_279.jpg": {"correct_code": "A58", "coordinate": [537, 432], "correct_codes": ["E36", "J13", "V39", "A52", "T76", "N36", "D74", "E14", "A58", "B24"]}, "../public/img/sentinel/sentinel_280.jpg": {"correct_code": "T24", "coordinate": [287, 129], "correct_codes": ["T24", "L98", "T53", "D73", "J59", "B12", "H94", "A73", "C97", "D13"]}, "../public/img/sentinel/sentinel_281.jpg": {"correct_code": "Y98", "coordinate": [764, 236], "correct_codes": ["W35", "D64", "C25", "S94", "F84", "N52", "Y98", "S34", "A64"]}, "../public/img/sentinel/sentinel_282.jpg": {"correct_code": "V72", "coordinate": [268, 395], "correct_codes": ["X53", "P49", "N42", "A38", "H79", "V72", "A41", "T98", "C57"]}, "../public/img/sentinel/sentinel_283.jpg": {"correct_code": "R57", "coordinate": [274, 498], "correct_codes": ["R57", "L75", "N97", "C34", "U53", "W61", "L89", "Z84", "X71"]}, "../public/img/sentinel/sentinel_284.jpg": {"correct_code": "Q45", "coordinate": [693, 123], "correct_codes": ["Q89", "E71", "X41", "Q45", "J96", "T69", "K19", "D18", "E68"]}, "../public/img/sentinel/sentinel_285.jpg": {"correct_code": "L29", "coordinate": [763, 609], "correct_codes": ["Z73", "M78", "A98", "F15", "T39", "Z72", "L29", "W52", "L16"]}, "../public/img/sentinel/sentinel_286.jpg": {"correct_code": "R52", "coordinate": [1000, 336], "correct_codes": ["H71", "V34", "J56", "R52", "D57", "L71", "V19", "H85", "P41", "S45"]}, "../public/img/sentinel/sentinel_287.jpg": {"correct_code": "E13", "coordinate": [441, 373], "correct_codes": ["M75", "Y93", "G31", "V41", "E13", "U73", "K84", "F93", "R25", "M89"]}, "../public/img/sentinel/sentinel_288.jpg": {"correct_code": "S36", "coordinate": [863, 334], "correct_codes": ["T52", "E67", "T75", "V39", "M48", "U65", "S36", "M19", "Y96", "P43"]}, "../public/img/sentinel/sentinel_289.jpg": {"correct_code": "L71", "coordinate": [840, 555], "correct_codes": ["P63", "W82", "C98", "Y87", "T63", "V31", "L71", "D95", "E83", "A49", "X93"]}, "../public/img/sentinel/sentinel_290.jpg": {"correct_code": "R46", "coordinate": [690, 127], "correct_codes": ["R46", "J69", "Q74", "G24", "D34", "A16", "Q63", "H49", "V95"]}, "../public/img/sentinel/sentinel_291.jpg": {"correct_code": "Y94", "coordinate": [120, 421], "correct_codes": ["Y94", "S14", "H82", "U62", "T28", "S78", "W97", "E47", "S45", "W67"]}, "../public/img/sentinel/sentinel_292.jpg": {"correct_code": "X51", "coordinate": [196, 329], "correct_codes": ["E41", "K38", "F59", "E62", "X51", "T17", "S81", "X81", "S48", "Q59"]}, "../public/img/sentinel/sentinel_293.jpg": {"correct_code": "N12", "coordinate": [772, 334], "correct_codes": ["R26", "P38", "U42", "D26", "B53", "R97", "R14", "N12", "A59", "Q86"]}, "../public/img/sentinel/sentinel_294.jpg": {"correct_code": "L89", "coordinate": [684, 445], "correct_codes": ["S25", "D41", "E64", "H82", "B95", "L89", "J71", "Y53", "R73", "S64"]}, "../public/img/sentinel/sentinel_295.jpg": {"correct_code": "R34", "coordinate": [265, 138], "correct_codes": ["R34", "B51", "G26", "E31", "X76", "N59", "W37", "T85", "D58", "P98", "V35"]}, "../public/img/sentinel/sentinel_296.jpg": {"correct_code": "N53", "coordinate": [603, 396], "correct_codes": ["H95", "H64", "N53", "W94", "W65", "W28", "D13", "Y83", "X21", "M18"]}, "../public/img/sentinel/sentinel_297.jpg": {"correct_code": "W75", "coordinate": [105, 277], "correct_codes": ["Z26", "V98", "M81", "U43", "Q29", "E28", "S68", "K81", "W75", "F57"]}, "../public/img/sentinel/sentinel_298.jpg": {"correct_code": "H54", "coordinate": [691, 598], "correct_codes": ["H54", "A65", "A25", "N91", "Z59", "U21", "J54", "V97", "S64"]}, "../public/img/sentinel/sentinel_299.jpg": {"correct_code": "D65", "coordinate": [344, 549], "correct_codes": ["J42", "S71", "P47", "M91", "R32", "E61", "D65", "A53", "C18", "P21"]}, "../public/img/sentinel/sentinel_300.jpg": {"correct_code": "B89", "coordinate": [1065, 132], "correct_codes": ["E94", "J59", "G58", "F54", "E37", "B89", "A43", "W18", "F96", "H15", "L39"]}, "../public/img/sentinel/sentinel_301.jpg": {"correct_code": "A24", "coordinate": [610, 440], "correct_codes": ["F46", "H92", "A24", "A26", "T72", "S61", "Y26", "G93", "J49", "L39"]}, "../public/img/sentinel/sentinel_302.jpg": {"correct_code": "P32", "coordinate": [591, 605], "correct_codes": ["P32", "W96", "L19", "Z93", "D86", "N43", "M56", "Y37"]}, "../public/img/sentinel/sentinel_303.jpg": {"correct_code": "T94", "coordinate": [1177, 437], "correct_codes": ["Y25", "Q36", "B38", "T94", "P37", "N12", "F58", "F87"]}, "../public/img/sentinel/sentinel_304.jpg": {"correct_code": "J56", "coordinate": [435, 541], "correct_codes": ["J56", "Y72", "A79", "T51", "M48", "V81", "L41", "F87", "L64", "K37", "P62"]}, "../public/img/sentinel/sentinel_305.jpg": {"correct_code": "Z65", "coordinate": [431, 172], "correct_codes": ["R35", "Y25", "Z65", "D73", "G36", "H92", "S36", "K41", "H69"]}, "../public/img/sentinel/sentinel_306.jpg": {"correct_code": "Y23", "coordinate": [856, 402], "correct_codes": ["R21", "P64", "M57", "S38", "Z24", "Q84", "A54", "U68", "K76", "Y23"]}, "../public/img/sentinel/sentinel_307.jpg": {"correct_code": "X18", "coordinate": [257, 383], "correct_codes": ["X18", "Y35", "E25", "Q21", "L36", "M67", "L32", "V85", "N29", "R63", "Y37"]}, "../public/img/sentinel/sentinel_308.jpg": {"correct_code": "Y58", "coordinate": [657, 268], "correct_codes": ["T93", "D56", "G87", "Y58", "G28", "N95", "T38", "L67", "U32", "U58", "W75"]}, "../public/img/sentinel/sentinel_309.jpg": {"correct_code": "K28", "coordinate": [1161, 346], "correct_codes": ["A47", "J78", "P53", "V31", "K15", "K28", "T95"]}, "../public/img/sentinel/sentinel_310.jpg": {"correct_code": "U72", "coordinate": [274, 117], "correct_codes": ["A47", "H13", "Q15", "J79", "J96", "E32", "S81", "U72", "B74", "S35"]}, "../public/img/sentinel/sentinel_311.jpg": {"correct_code": "N21", "coordinate": [822, 408], "correct_codes": ["J12", "U71", "N21", "J83", "R45", "K67", "X26", "T14", "Y51"]}, "../public/img/sentinel/sentinel_312.jpg": {"correct_code": "K73", "coordinate": [273, 408], "correct_codes": ["B39", "U49", "K73", "R27", "D75", "W34", "S62", "G52", "D86", "B89"]}, "../public/img/sentinel/sentinel_313.jpg": {"correct_code": "R36", "coordinate": [346, 422], "correct_codes": ["Y97", "R36", "Z95", "H71", "F51", "X46", "V47", "V31", "G43", "M13"]}, "../public/img/sentinel/sentinel_314.jpg": {"correct_code": "G41", "coordinate": [201, 159], "correct_codes": ["H36", "G41", "C75", "Q15", "R24", "B92", "S39", "G29"]}, "../public/img/sentinel/sentinel_315.jpg": {"correct_code": "E86", "coordinate": [1171, 128], "correct_codes": ["Y91", "R57", "E86", "C32", "W49", "Y81", "L29"]}, "../public/img/sentinel/sentinel_316.jpg": {"correct_code": "N53", "coordinate": [848, 184], "correct_codes": ["E38", "J14", "W38", "S46", "A97", "N53", "K95", "E54", "H21"]}, "../public/img/sentinel/sentinel_317.jpg": {"correct_code": "G85", "coordinate": [1074, 207], "correct_codes": ["A89", "Q26", "S78", "S42", "N15", "L92", "M59", "G85", "V18"]}, "../public/img/sentinel/sentinel_318.jpg": {"correct_code": "J53", "coordinate": [370, 348], "correct_codes": ["R61", "D15", "H92", "X72", "W26", "Z76", "A92", "Q94", "J53", "K68"]}, "../public/img/sentinel/sentinel_319.jpg": {"correct_code": "T45", "coordinate": [668, 218], "correct_codes": ["H58", "W89", "B93", "F94", "A61", "T45", "S45", "V95", "G63", "W42"]}, "../public/img/sentinel/sentinel_320.jpg": {"correct_code": "C78", "coordinate": [180, 431], "correct_codes": ["V13", "K23", "M87", "H52", "U28", "L82", "D92", "C78", "T67"]}, "../public/img/sentinel/sentinel_321.jpg": {"correct_code": "H72", "coordinate": [595, 591], "correct_codes": ["C83", "R76", "W58", "H72", "J59", "A72", "G36", "B13", "W12", "L12", "V67"]}, "../public/img/sentinel/sentinel_322.jpg": {"correct_code": "L18", "coordinate": [919, 483], "correct_codes": ["E72", "G27", "H89", "J84", "C68", "W93", "K26", "E45", "R14", "L18"]}, "../public/img/sentinel/sentinel_323.jpg": {"correct_code": "Y52", "coordinate": [903, 492], "correct_codes": ["H97", "T56", "Y87", "W12", "X75", "Z29", "H87", "Y52", "B19", "K19"]}, "../public/img/sentinel/sentinel_324.jpg": {"correct_code": "B54", "coordinate": [744, 278], "correct_codes": ["W68", "T12", "V59", "Y75", "B54", "R81", "S98", "Z31", "N74", "Q65"]}, "../public/img/sentinel/sentinel_325.jpg": {"correct_code": "F81", "coordinate": [612, 606], "correct_codes": ["T16", "C83", "F37", "K59", "E27", "W49", "D12", "W43", "F81"]}, "../public/img/sentinel/sentinel_326.jpg": {"correct_code": "A53", "coordinate": [195, 345], "correct_codes": ["S93", "S73", "V12", "G56", "G19", "K71", "A53", "L85", "Y84"]}, "../public/img/sentinel/sentinel_327.jpg": {"correct_code": "Q61", "coordinate": [692, 221], "correct_codes": ["G57", "M31", "B82", "L72", "Y45", "Q61", "F72", "C27", "Y84", "B83"]}, "../public/img/sentinel/sentinel_328.jpg": {"correct_code": "G75", "coordinate": [768, 545], "correct_codes": ["L43", "X82", "P45", "G75", "X84", "B35", "M17", "J71", "Z46", "P62"]}, "../public/img/sentinel/sentinel_329.jpg": {"correct_code": "W23", "coordinate": [359, 610], "correct_codes": ["W23", "L91", "Q45", "E54", "G92", "Q48", "V84", "D18"]}, "../public/img/sentinel/sentinel_330.jpg": {"correct_code": "A69", "coordinate": [1020, 245], "correct_codes": ["R41", "A69", "W87", "U97", "Y72", "M38", "K56", "T21", "Y18", "X36"]}, "../public/img/sentinel/sentinel_331.jpg": {"correct_code": "B46", "coordinate": [939, 447], "correct_codes": ["Q57", "R57", "F37", "V52", "V94", "B46", "Z78", "C54", "U45", "S34"]}, "../public/img/sentinel/sentinel_332.jpg": {"correct_code": "G26", "coordinate": [681, 619], "correct_codes": ["P29", "R58", "G26", "D51", "R24", "F43", "B36", "J43", "A42"]}, "../public/img/sentinel/sentinel_333.jpg": {"correct_code": "C39", "coordinate": [125, 134], "correct_codes": ["C39", "V82", "Y59", "J95", "Z94", "P61", "T58", "Y53", "U12"]}, "../public/img/sentinel/sentinel_334.jpg": {"correct_code": "V98", "coordinate": [589, 333], "correct_codes": ["P86", "H38", "M46", "P89", "T49", "V98", "L68", "J37", "A59", "P71"]}, "../public/img/sentinel/sentinel_335.jpg": {"correct_code": "S64", "coordinate": [115, 461], "correct_codes": ["W79", "L25", "E46", "J72", "U45", "X15", "Q12", "S64"]}, "../public/img/sentinel/sentinel_336.jpg": {"correct_code": "L29", "coordinate": [283, 178], "correct_codes": ["S13", "Z79", "D48", "R14", "M51", "Q62", "L29", "S64"]}, "../public/img/sentinel/sentinel_337.jpg": {"correct_code": "T62", "coordinate": [1082, 578], "correct_codes": ["B39", "A93", "J67", "L97", "K67", "M34", "D74", "M13", "N87", "H15", "T62"]}, "../public/img/sentinel/sentinel_338.jpg": {"correct_code": "U42", "coordinate": [266, 124], "correct_codes": ["S32", "S89", "H19", "H32", "D97", "U42", "H96", "K76", "V71"]}, "../public/img/sentinel/sentinel_339.jpg": {"correct_code": "V52", "coordinate": [920, 545], "correct_codes": ["X12", "G38", "W29", "C94", "K78", "Q73", "V52", "G92", "W63", "S64"]}, "../public/img/sentinel/sentinel_340.jpg": {"correct_code": "R95", "coordinate": [673, 531], "correct_codes": ["H97", "U85", "Y74", "N51", "J38", "F91", "R95", "C19", "W42", "Y23"]}, "../public/img/sentinel/sentinel_341.jpg": {"correct_code": "B85", "coordinate": [1112, 213], "correct_codes": ["V61", "L53", "J94", "B54", "T73", "K84", "G83", "B85"]}, "../public/img/sentinel/sentinel_342.jpg": {"correct_code": "R45", "coordinate": [832, 110], "correct_codes": ["A63", "D54", "Y43", "R45", "J92", "N23", "V92", "E83", "L21", "S26"]}, "../public/img/sentinel/sentinel_343.jpg": {"correct_code": "G75", "coordinate": [736, 234], "correct_codes": ["G94", "J21", "T75", "Y17", "G75", "G24", "F79", "B95", "X31"]}, "../public/img/sentinel/sentinel_344.jpg": {"correct_code": "S13", "coordinate": [767, 187], "correct_codes": ["Z14", "S13", "M78", "G95", "L68", "K97", "C58", "V84", "Q29", "T98", "D96"]}, "../public/img/sentinel/sentinel_345.jpg": {"correct_code": "X16", "coordinate": [349, 352], "correct_codes": ["Y93", "Y61", "N51", "A32", "X16", "A23", "C96", "K84", "V91", "C27"]}, "../public/img/sentinel/sentinel_346.jpg": {"correct_code": "B28", "coordinate": [434, 615], "correct_codes": ["S83", "L75", "B28", "S59", "Z73", "J96", "G82", "U83", "B37"]}, "../public/img/sentinel/sentinel_347.jpg": {"correct_code": "H86", "coordinate": [1024, 112], "correct_codes": ["J74", "Z52", "W83", "X76", "M25", "A24", "T47", "H86", "P85"]}, "../public/img/sentinel/sentinel_348.jpg": {"correct_code": "U68", "coordinate": [708, 291], "correct_codes": ["V36", "F37", "M83", "P95", "V49", "U87", "Q67", "C58", "U68", "Y21"]}, "../public/img/sentinel/sentinel_349.jpg": {"correct_code": "B62", "coordinate": [111, 163], "correct_codes": ["Q47", "P73", "L56", "F61", "Q15", "B62", "Z29", "R51", "V16", "X26"]}, "../public/img/sentinel/sentinel_350.jpg": {"correct_code": "G36", "coordinate": [105, 373], "correct_codes": ["S96", "G36", "C91", "M65", "V73", "S39", "E28", "X43", "X83", "A46"]}, "../public/img/sentinel/sentinel_351.jpg": {"correct_code": "M97", "coordinate": [1017, 599], "correct_codes": ["Q42", "L27", "C59", "A93", "D52", "S12", "M97", "Z38", "R15", "N52"]}, "../public/img/sentinel/sentinel_352.jpg": {"correct_code": "R91", "coordinate": [1027, 337], "correct_codes": ["W81", "N91", "Y86", "C63", "D39", "R91", "T82", "H62", "T32", "J76"]}, "../public/img/sentinel/sentinel_353.jpg": {"correct_code": "G36", "coordinate": [752, 230], "correct_codes": ["G36", "T51", "V39", "F51", "C16", "T65", "M28", "W45", "B58", "Q13"]}, "../public/img/sentinel/sentinel_354.jpg": {"correct_code": "X16", "coordinate": [906, 394], "correct_codes": ["H14", "R58", "L53", "Z34", "U69", "X16", "J85"]}, "../public/img/sentinel/sentinel_355.jpg": {"correct_code": "Y36", "coordinate": [118, 344], "correct_codes": ["L58", "N18", "T54", "Y36", "N16", "C75", "J94", "G18", "C34", "B37"]}, "../public/img/sentinel/sentinel_356.jpg": {"correct_code": "P71", "coordinate": [425, 606], "correct_codes": ["E93", "S29", "D63", "U95", "F71", "Q58", "U52", "P71", "K75", "T29"]}, "../public/img/sentinel/sentinel_357.jpg": {"correct_code": "J36", "coordinate": [919, 109], "correct_codes": ["Y97", "H17", "E24", "Y62", "J36", "L62", "M17", "Q32"]}, "../public/img/sentinel/sentinel_358.jpg": {"correct_code": "G65", "coordinate": [572, 347], "correct_codes": ["P86", "X18", "C62", "L68", "G91", "E69", "T85", "X81", "G65"]}, "../public/img/sentinel/sentinel_359.jpg": {"correct_code": "L53", "coordinate": [1015, 279], "correct_codes": ["L53", "S73", "Z67", "F31", "H65", "F75", "T78", "F93", "R16", "X95"]}, "../public/img/sentinel/sentinel_360.jpg": {"correct_code": "V25", "coordinate": [290, 276], "correct_codes": ["Y19", "L76", "A52", "A83", "L54", "V25", "M35", "B83", "A46"]}, "../public/img/sentinel/sentinel_361.jpg": {"correct_code": "Z32", "coordinate": [669, 233], "correct_codes": ["X54", "Z32", "F67", "P19", "J67", "N16", "H73", "H53", "T45", "V71"]}, "../public/img/sentinel/sentinel_362.jpg": {"correct_code": "P93", "coordinate": [524, 455], "correct_codes": ["V48", "E15", "C56", "J32", "R95", "W54", "P93", "Z48", "E56"]}, "../public/img/sentinel/sentinel_363.jpg": {"correct_code": "U89", "coordinate": [738, 601], "correct_codes": ["Y82", "Y19", "M58", "M82", "Z71", "Q79", "U89", "L45"]}, "../public/img/sentinel/sentinel_364.jpg": {"correct_code": "D76", "coordinate": [1017, 109], "correct_codes": ["U51", "C38", "W85", "R26", "K74", "T48", "J45", "D76", "N29", "G85"]}, "../public/img/sentinel/sentinel_365.jpg": {"correct_code": "M83", "coordinate": [795, 263], "correct_codes": ["Z15", "Z85", "M83", "Y17", "X49", "Q37", "Z31", "U83", "F49", "V18"]}, "../public/img/sentinel/sentinel_366.jpg": {"correct_code": "K51", "coordinate": [604, 327], "correct_codes": ["S93", "W78", "K51", "Z12", "A76", "T78", "P64", "U95", "Y98"]}, "../public/img/sentinel/sentinel_367.jpg": {"correct_code": "J41", "coordinate": [429, 280], "correct_codes": ["Q98", "H95", "J21", "M53", "P16", "C24", "Z34", "F26", "U63", "J41"]}, "../public/img/sentinel/sentinel_368.jpg": {"correct_code": "M41", "coordinate": [667, 167], "correct_codes": ["A69", "W41", "L58", "M41", "M58", "V64", "U48", "G78", "J76"]}, "../public/img/sentinel/sentinel_369.jpg": {"correct_code": "P28", "coordinate": [1083, 234], "correct_codes": ["P28", "F45", "J58", "W83", "A89", "P53", "T84", "C51", "L34"]}, "../public/img/sentinel/sentinel_370.jpg": {"correct_code": "V84", "coordinate": [865, 226], "correct_codes": ["S83", "C75", "K64", "F79", "R24", "Q53", "T39", "C69", "V84"]}, "../public/img/sentinel/sentinel_371.jpg": {"correct_code": "Y85", "coordinate": [696, 375], "correct_codes": ["J14", "V28", "C73", "Q74", "P18", "N32", "Y85", "L68", "M67", "Q64"]}, "../public/img/sentinel/sentinel_372.jpg": {"correct_code": "D98", "coordinate": [757, 380], "correct_codes": ["D98", "T12", "U86", "Z73", "R79", "W45", "H74", "G37", "U12", "H93"]}, "../public/img/sentinel/sentinel_373.jpg": {"correct_code": "F98", "coordinate": [267, 113], "correct_codes": ["B25", "A74", "D35", "M48", "D27", "D74", "B94", "G52", "F98", "A53"]}, "../public/img/sentinel/sentinel_374.jpg": {"correct_code": "W56", "coordinate": [425, 403], "correct_codes": ["W56", "P51", "K85", "E43", "A16", "D91", "R14", "W46", "D86", "W96"]}, "../public/img/sentinel/sentinel_375.jpg": {"correct_code": "L75", "coordinate": [1155, 514], "correct_codes": ["A47", "L75", "V59", "C87", "J46", "Y58", "N29"]}, "../public/img/sentinel/sentinel_376.jpg": {"correct_code": "V19", "coordinate": [995, 341], "correct_codes": ["L75", "E86", "V39", "Y35", "F78", "F26", "P79", "V19", "T45", "Q91"]}, "../public/img/sentinel/sentinel_377.jpg": {"correct_code": "J61", "coordinate": [658, 601], "correct_codes": ["E98", "B51", "D51", "E32", "C54", "J61", "A57", "Q63", "L35"]}, "../public/img/sentinel/sentinel_378.jpg": {"correct_code": "X23", "coordinate": [854, 126], "correct_codes": ["J26", "W62", "R61", "K23", "G27", "D39", "T19", "X23", "G72", "V17"]}, "../public/img/sentinel/sentinel_379.jpg": {"correct_code": "U13", "coordinate": [1087, 243], "correct_codes": ["Y61", "G25", "F54", "G84", "Q19", "S54", "H87", "D18", "U13"]}, "../public/img/sentinel/sentinel_380.jpg": {"correct_code": "T18", "coordinate": [864, 508], "correct_codes": ["S76", "U93", "G31", "N42", "V41", "X69", "T18", "X51", "L67", "P87"]}, "../public/img/sentinel/sentinel_381.jpg": {"correct_code": "X47", "coordinate": [844, 290], "correct_codes": ["L14", "H24", "R85", "X47", "L71", "A42", "X81", "N87", "Q13", "G23"]}, "../public/img/sentinel/sentinel_382.jpg": {"correct_code": "T21", "coordinate": [189, 117], "correct_codes": ["R35", "Q57", "L58", "Z12", "X35", "J96", "V69", "K54", "T21", "F34"]}, "../public/img/sentinel/sentinel_383.jpg": {"correct_code": "S92", "coordinate": [447, 597], "correct_codes": ["Y95", "S92", "L56", "C73", "U18", "Y76", "U16", "T14", "Y83"]}, "../public/img/sentinel/sentinel_384.jpg": {"correct_code": "D17", "coordinate": [1013, 445], "correct_codes": ["A97", "D17", "D43", "R97", "C82", "Z72", "B67", "L35", "J64", "V76"]}, "../public/img/sentinel/sentinel_385.jpg": {"correct_code": "Q31", "coordinate": [195, 124], "correct_codes": ["R72", "T92", "Y43", "P42", "Z43", "C16", "A56", "M29", "V42", "S84", "Q31"]}, "../public/img/sentinel/sentinel_386.jpg": {"correct_code": "G57", "coordinate": [859, 250], "correct_codes": ["G57", "R76", "S92", "V46", "U65", "K49", "C61", "V81", "T73", "K15"]}, "../public/img/sentinel/sentinel_387.jpg": {"correct_code": "Z68", "coordinate": [843, 396], "correct_codes": ["T53", "N21", "Z68", "L78", "H75", "S38", "J61", "H96", "L81", "S18", "M15"]}, "../public/img/sentinel/sentinel_388.jpg": {"correct_code": "C41", "coordinate": [103, 237], "correct_codes": ["J12", "P28", "W62", "J67", "C41", "N53", "Y81", "J29", "J54"]}, "../public/img/sentinel/sentinel_389.jpg": {"correct_code": "V15", "coordinate": [428, 195], "correct_codes": ["F27", "G46", "D98", "T56", "V15", "V98", "V49", "Q23", "L41", "K32"]}, "../public/img/sentinel/sentinel_390.jpg": {"correct_code": "U19", "coordinate": [539, 230], "correct_codes": ["J14", "R72", "V54", "N53", "D91", "M84", "U19", "M17", "P65", "R63"]}, "../public/img/sentinel/sentinel_391.jpg": {"correct_code": "Q39", "coordinate": [678, 528], "correct_codes": ["H37", "N75", "C29", "G64", "H63", "K27", "D69", "Y84", "Q39", "X62"]}, "../public/img/sentinel/sentinel_392.jpg": {"correct_code": "K45", "coordinate": [264, 556], "correct_codes": ["M75", "G41", "L97", "M73", "F69", "K59", "P64", "K45", "J62", "H74", "K16"]}, "../public/img/sentinel/sentinel_393.jpg": {"correct_code": "W57", "coordinate": [601, 240], "correct_codes": ["W57", "C83", "W47", "Q19", "Z39", "S36", "K72", "E25", "K84", "K54"]}, "../public/img/sentinel/sentinel_394.jpg": {"correct_code": "F34", "coordinate": [610, 335], "correct_codes": ["H59", "X85", "U38", "M91", "A36", "L73", "P25", "W34", "V91", "F34"]}, "../public/img/sentinel/sentinel_395.jpg": {"correct_code": "Q75", "coordinate": [697, 372], "correct_codes": ["Q75", "S67", "U76", "T74", "D82", "D51", "D92", "A21", "B67"]}, "../public/img/sentinel/sentinel_396.jpg": {"correct_code": "K34", "coordinate": [347, 124], "correct_codes": ["Y54", "R26", "K34", "U53", "T17", "E81", "P56", "K84", "K96", "F36"]}, "../public/img/sentinel/sentinel_397.jpg": {"correct_code": "L15", "coordinate": [981, 115], "correct_codes": ["T24", "L42", "J67", "G27", "T92", "V41", "Z38", "T73", "U68", "L15", "Y21"]}, "../public/img/sentinel/sentinel_398.jpg": {"correct_code": "S21", "coordinate": [420, 328], "correct_codes": ["X28", "A69", "Y91", "F68", "C52", "V69", "G65", "T25", "M35", "S21"]}, "../public/img/sentinel/sentinel_399.jpg": {"correct_code": "C93", "coordinate": [541, 299], "correct_codes": ["P74", "E17", "A26", "U87", "H73", "T69", "C96", "J53", "C93", "R63"]}}